{
  "_builderState": {
    "mode": "snomed-tree",
    "roots": [
      {
        "code": "405944004",
        "display": "Asthmatic bronchitis"
      },
      {
        "code": "13791008",
        "display": "Asthenia"
      }
    ],
    "decisions": [
      {
        "code": "405944004",
        "display": "Asthmatic bronchitis",
        "action": "include"
      },
      {
        "code": "13791008",
        "display": "Asthenia",
        "action": "include"
      },
      {
        "code": "272036004",
        "display": "Complaining of debility and malaise",
        "action": "exclude"
      },
      {
        "code": "161874006",
        "display": "Heavy feeling",
        "action": "exclude"
      },
      {
        "code": "18726006",
        "display": "Senile asthenia",
        "action": "exclude"
      }
    ],
    "search": {
      "query": "asth",
      "activeOnly": true,
      "refsetCode": "",
      "inspectingCode": "13791008"
    }
  },
  "_libraryMeta": {
    "changeLog": [
      {
        "author": "FrankiePH",
        "date": "2026-04-23T17:18:36.231327+00:00",
        "reason": "initial creation",
        "version": 1
      },
      {
        "version": 2,
        "reason": "test",
        "date": "2026-04-23T17:20:30.107821+00:00",
        "author": "FrankiePH"
      }
    ],
    "collection": "Demo2",
    "createdBy": "FrankiePH",
    "slug": "search-and-build-made-value-set",
    "updatedAt": "2026-04-23T17:20:30.107821+00:00",
    "version": 2
  },
  "compose": {
    "exclude": [
      {
        "concept": [
          {
            "code": "272036004",
            "display": "Complaining of debility and malaise"
          },
          {
            "code": "161874006",
            "display": "Heavy feeling"
          },
          {
            "code": "18726006",
            "display": "Senile asthenia"
          }
        ],
        "system": "http://snomed.info/sct"
      }
    ],
    "include": [
      {
        "concept": [
          {
            "code": "405944004",
            "display": "Asthmatic bronchitis"
          },
          {
            "code": "13791008",
            "display": "Asthenia"
          }
        ],
        "system": "http://snomed.info/sct"
      }
    ]
  },
  "description": "This is a test",
  "name": "SearchBuild",
  "resourceType": "ValueSet",
  "status": "draft",
  "text": {
    "div": "<div xmlns=\"http://www.w3.org/1999/xhtml\"><p>Search and Build Made Value Set</p></div>",
    "status": "generated"
  },
  "title": "Search and Build Made Value Set",
  "url": "https://ramseysystems.co.uk/fhir/ValueSet/searchbuild-2053fdd8c28d"
}